test/__init__.py
test/test_default_api.py
chino_io_scriba-0.0.0.dist-info/METADATA
chino_io_scriba-0.0.0.dist-info/WHEEL
chino_io_scriba-0.0.0.dist-info/top_level.txt
chino_io_scriba-0.0.0.dist-info/RECORD
