Metadata-Version: 2.1
Name: chino-io-scriba
Version: 0.0.0
Summary: Chino.io Scriba SDK Python
Home-page: https://www.chino.io
Author-email: 
License: UNKNOWN
Keywords: Chino.io Scriba API
Platform: UNKNOWN
Requires-Dist: urllib3 (>=1.15)
Requires-Dist: six (>=1.10)
Requires-Dist: certifi
Requires-Dist: python-dateutil
